pystubgen.py
setup.cfg
setup.py
pystubgen.egg-info/PKG-INFO
pystubgen.egg-info/SOURCES.txt
pystubgen.egg-info/dependency_links.txt
pystubgen.egg-info/entry_points.txt
pystubgen.egg-info/top_level.txt