Metadata-Version: 1.1
Name: pystubgen
Version: 0.1
Summary: Generates Python source code from a module for documentation purposes
Home-page: https://github.com/Lekensteyn/pystubgen
Author: Peter Wu
Author-email: peter@lekensteyn.nl
License: MIT
Keywords: development documentation
Platform: UNKNOWN
Classifier: Development Status :: 3 - Alpha
Classifier: Intended Audience :: Developers
Classifier: Topic :: Software Development :: Code Generators
Classifier: Topic :: Software Development :: Documentation
Classifier: License :: OSI Approved :: MIT License
Classifier: Programming Language :: Python :: 2
Classifier: Programming Language :: Python :: 2.6
Classifier: Programming Language :: Python :: 2.7
Classifier: Programming Language :: Python :: 3
Classifier: Programming Language :: Python :: 3.2
Classifier: Programming Language :: Python :: 3.4
